hmsclient/__init__.py
hmsclient/hmsclient.py
hmsclient/genthrift/__init__.py
hmsclient/genthrift/fb303/FacebookService.py
hmsclient/genthrift/fb303/__init__.py
hmsclient/genthrift/fb303/constants.py
hmsclient/genthrift/fb303/ttypes.py
hmsclient/genthrift/hive_metastore/ThriftHiveMetastore.py
hmsclient/genthrift/hive_metastore/__init__.py
hmsclient/genthrift/hive_metastore/constants.py
hmsclient/genthrift/hive_metastore/ttypes.py
hmsclient-0.1.0.dist-info/METADATA
hmsclient-0.1.0.dist-info/RECORD
hmsclient-0.1.0.dist-info/WHEEL
hmsclient-0.1.0.dist-info/top_level.txt
