Metadata-Version: 2.1
Name: hmsclient
Version: 0.1.0
Summary: A package interact with the Hive metastore via the Thrift protocol
Home-page: https://github.com/gglanzani/hmsclient
Author: Giovanni Lanzani
Author-email: giovanni@lanzani.nl
License: Apache 2.0
Keywords: hive data database thrift metastore
Platform: UNKNOWN
Classifier: Development Status :: 4 - Beta
Classifier: Intended Audience :: Information Technology
Classifier: Topic :: Database
Classifier: License :: OSI Approved :: Apache Software License
Classifier: Programming Language :: Python :: 3
Classifier: Programming Language :: Python :: 3.5
Classifier: Programming Language :: Python :: 3.6
Requires-Dist: thrift
Requires-Dist: click
Provides-Extra: dev
Requires-Dist: pytest; extra == 'dev'
Provides-Extra: test
Requires-Dist: pytest; extra == 'test'
